kim_convergence/__init__.py
kim_convergence/_default.py
kim_convergence/_version.py
kim_convergence/batch.py
kim_convergence/err.py
kim_convergence/outlier.py
kim_convergence/run_length_control.py
kim_convergence/scale.py
kim_convergence/utils.py
kim_convergence/stats/__init__.py
kim_convergence/stats/beta_dist.py
kim_convergence/stats/nonnormal_test.py
kim_convergence/stats/normal_dist.py
kim_convergence/stats/normal_test.py
kim_convergence/stats/randomness_test.py
kim_convergence/stats/t_dist.py
kim_convergence/stats/tools.py
kim_convergence/stats/zero_rc.py
kim_convergence/stats/zero_rc_bounds.py
kim_convergence/timeseries/__init__.py
kim_convergence/timeseries/equilibration_length.py
kim_convergence/timeseries/geweke.py
kim_convergence/timeseries/statistical_inefficiency.py
kim_convergence/timeseries/utils.py
kim_convergence/ucl/__init__.py
kim_convergence/ucl/mser_m.py
kim_convergence/ucl/mser_m_y.py
kim_convergence/ucl/n_skart.py
kim_convergence/ucl/ucl_base.py
kim_convergence/ucl/uncorrelated_samples.py
kim_convergence/ucl/spectral/__init__.py
kim_convergence/ucl/spectral/heidelberger_welch.py
kim_convergence-0.0.3.dist-info/licenses/LICENSE
kim_convergence-0.0.3.dist-info/METADATA
kim_convergence-0.0.3.dist-info/WHEEL
kim_convergence-0.0.3.dist-info/top_level.txt
kim_convergence-0.0.3.dist-info/RECORD
