Metadata-Version: 2.4
Name: kim-convergence
Version: 0.0.3
Summary: kim-convergence designed to help in automatic equilibration detection & run length control.
Author-email: Yaser Afshar <ya.afshar@gmail.com>
Maintainer-email: Yaser Afshar <ya.afshar@gmail.com>
License-Expression: LGPL-2.1-or-later
Project-URL: Homepage, https://github.com/openkim/kim-convergence
Project-URL: Issues, https://github.com/openkim/kim-convergence/issues
Keywords: convergence,automated equilibration detection,run length control,upper confidence limit,confidence interval
Classifier: Development Status :: 4 - Beta
Classifier: Intended Audience :: Science/Research
Classifier: Topic :: Scientific/Engineering
Classifier: Operating System :: OS Independent
Classifier: Programming Language :: Python :: 3
Requires-Python: >=3.9
License-File: LICENSE
Requires-Dist: numpy>1.16
Requires-Dist: scipy
Requires-Dist: kim-edn>1.4.0
Requires-Dist: joblib
Dynamic: license-file
